htmlcmd-1.1.0.dist-info/licenses/LICENSE
mcp/__init__.py
mcp/__main__.py
mcp/cli.py
mcp/config.py
mcp/content_parser.py
mcp/logger.py
mcp/markdown_converter.py
mcp/page_fetcher.py
mcp/plugin.py
mcp/plugins/__init__.py
mcp/plugins/image_downloader.py
mcp/plugins/image_processor.py
htmlcmd-1.1.0.dist-info/METADATA
htmlcmd-1.1.0.dist-info/WHEEL
htmlcmd-1.1.0.dist-info/entry_points.txt
htmlcmd-1.1.0.dist-info/top_level.txt
htmlcmd-1.1.0.dist-info/RECORD
